<?xml version="1.0" encoding="UTF-8"?>
<record_update sys_domain="global" table="sysrule_assignment">
    <sysrule_assignment action="INSERT_OR_UPDATE">
        <active>true</active>
        <condition/>
        <description/>
        <group display_value="Maintenance" name="Maintenance">d115a93d4f1e2200c17782818110c729</group>
        <match_conditions>ALL</match_conditions>
        <name>Default assignment</name>
        <order>1000</order>
        <script>/**&#13;
* Example:&#13;
* The following script requires personalizing the instance to add the Malware category and the Security assignment group.&#13;
* if (current.category == "Hardware")&#13;
*    current.assignment_group.setDisplayValue("Hardware"); &#13;
* else if (current.category == "Software")&#13;
*    current.assignment_group.setDisplayValue("Software");&#13;
* else if (current.category == "Malware")&#13;
*    current.assignment_group.setDisplayValue("Security");	&#13;
*&#13;
* Another Example:&#13;
* Release Planning Example, which assigns the last person assigned to a release to the current release.&#13;
* current.release.product.service.assigned_to;&#13;
*/</script>
        <sys_class_name>sysrule_assignment</sys_class_name>
        <sys_created_by>admin</sys_created_by>
        <sys_created_on>2016-10-07 00:17:26</sys_created_on>
        <sys_customer_update>false</sys_customer_update>
        <sys_domain>global</sys_domain>
        <sys_domain_path>/</sys_domain_path>
        <sys_id>5a18697d4f1e2200c17782818110c7c9</sys_id>
        <sys_mod_count>1</sys_mod_count>
        <sys_name>Default assignment</sys_name>
        <sys_overrides/>
        <sys_package display_value="Hotel" source="x_hotel">a8f395beebc522004fcde08a5206fe2e</sys_package>
        <sys_policy/>
        <sys_replace_on_upgrade>false</sys_replace_on_upgrade>
        <sys_scope display_value="Hotel">a8f395beebc522004fcde08a5206fe2e</sys_scope>
        <sys_update_name>sysrule_assignment_5a18697d4f1e2200c17782818110c7c9</sys_update_name>
        <sys_updated_by>admin</sys_updated_by>
        <sys_updated_on>2016-10-07 00:18:48</sys_updated_on>
        <table>x_hotel_maintenance</table>
        <user/>
    </sysrule_assignment>
</record_update>
